discord/__init__.py
discord/__main__.py
discord/abc.py
discord/activity.py
discord/appinfo.py
discord/application_commands.py
discord/asset.py
discord/audit_logs.py
discord/backoff.py
discord/channel.py
discord/client.py
discord/colour.py
discord/components.py
discord/context_managers.py
discord/embeds.py
discord/emoji.py
discord/enums.py
discord/errors.py
discord/file.py
discord/flags.py
discord/gateway.py
discord/guild.py
discord/guild_scheduled_event.py
discord/http.py
discord/integrations.py
discord/interactions.py
discord/invite.py
discord/iterators.py
discord/member.py
discord/mentions.py
discord/message.py
discord/mixins.py
discord/object.py
discord/oggparse.py
discord/opus.py
discord/partial_emoji.py
discord/permissions.py
discord/player.py
discord/py.typed
discord/raw_models.py
discord/reaction.py
discord/role.py
discord/shard.py
discord/stage_instance.py
discord/state.py
discord/sticker.py
discord/team.py
discord/template.py
discord/threads.py
discord/user.py
discord/utils.py
discord/voice_client.py
discord/welcome_screen.py
discord/widget.py
discord/bin/libopus-0.x64.dll
discord/bin/libopus-0.x86.dll
discord/ext/commands/__init__.py
discord/ext/commands/_types.py
discord/ext/commands/bot.py
discord/ext/commands/cog.py
discord/ext/commands/context.py
discord/ext/commands/converter.py
discord/ext/commands/cooldowns.py
discord/ext/commands/core.py
discord/ext/commands/errors.py
discord/ext/commands/flags.py
discord/ext/commands/help.py
discord/ext/commands/http_interactions.py
discord/ext/commands/view.py
discord/ext/tasks/__init__.py
discord/ext/vbu/__init__.py
discord/ext/vbu/__main__.py
discord/ext/vbu/runner.py
discord/ext/vbu/cogs/__init__.py
discord/ext/vbu/cogs/bot_stats.py
discord/ext/vbu/cogs/command_event.py
discord/ext/vbu/cogs/connect_event.py
discord/ext/vbu/cogs/error_handler.py
discord/ext/vbu/cogs/general_analytics.py
discord/ext/vbu/cogs/help_command.py
discord/ext/vbu/cogs/interaction_handler.py
discord/ext/vbu/cogs/owner_only.py
novus-0.2.5.dist-info/LICENSE
novus-0.2.5.dist-info/METADATA
novus-0.2.5.dist-info/WHEEL
novus-0.2.5.dist-info/entry_points.txt
novus-0.2.5.dist-info/top_level.txt
novus-0.2.5.dist-info/RECORD
