Metadata-Version: 2.1
Name: novus
Version: 0.2.5
Summary: A Python wrapper for the Discord API
Home-page: https://github.com/Voxel-Fox-Ltd/Novus
Author: Kae Bartlett
License: MIT
Project-URL: Documentation, https://novus.readthedocs.io/en/latest/
Project-URL: Issue tracker, https://github.com/Voxel-Fox-Ltd/Novus/issues
Classifier: Development Status :: 4 - Beta
Classifier: License :: OSI Approved :: MIT License
Classifier: Intended Audience :: Developers
Classifier: Natural Language :: English
Classifier: Operating System :: OS Independent
Classifier: Programming Language :: Python :: 3.8
Classifier: Programming Language :: Python :: 3.9
Classifier: Topic :: Internet
Classifier: Topic :: Software Development :: Libraries
Classifier: Topic :: Software Development :: Libraries :: Python Modules
Classifier: Topic :: Utilities
Classifier: Typing :: Typed
Requires-Python: >=3.8.0
License-File: LICENSE
Requires-Dist: aiohttp <4.0.0,>=3.6.0
Requires-Dist: PyNaCl <1.5,>=1.3.0
Provides-Extra: docs
Requires-Dist: sphinx ==4.0.2 ; extra == 'docs'
Requires-Dist: sphinxcontrib-trio ==1.1.2 ; extra == 'docs'
Requires-Dist: sphinxcontrib-websupport ; extra == 'docs'
Provides-Extra: speed
Requires-Dist: orjson >=3.5.4 ; extra == 'speed'
Requires-Dist: aiodns >=1.1 ; extra == 'speed'
Requires-Dist: Brotli ; extra == 'speed'
Requires-Dist: cchardet ; extra == 'speed'
Provides-Extra: vbu
Requires-Dist: toml ; extra == 'vbu'
Requires-Dist: aiosqlite ; extra == 'vbu'
Requires-Dist: aioredis <2.0,>=1.3 ; extra == 'vbu'
Requires-Dist: aioredlock <0.8,>=0.7.0 ; extra == 'vbu'
Requires-Dist: aiodogstatsd <0.15,>=0.14.0 ; extra == 'vbu'
Requires-Dist: upgradechatpy <2.0,>=1.0.3 ; extra == 'vbu'
Requires-Dist: cryptography ; extra == 'vbu'
Requires-Dist: aiohttp-jinja2 ; extra == 'vbu'
Requires-Dist: aiohttp-session ; extra == 'vbu'
Requires-Dist: jinja2 <4.0.0,>=3.0.0 ; extra == 'vbu'
Requires-Dist: markdown ; extra == 'vbu'
Requires-Dist: htmlmin ; extra == 'vbu'
Provides-Extra: voice
Requires-Dist: PyNaCl <1.5,>=1.3.0 ; extra == 'voice'
